Metadata-Version: 2.1
Name: FerriteLib
Version: 0.1
Summary: Load JSON at the speed of light!
Home-page: https://github.com/xemulat
Download-URL: https://github.com/xemulat/FerriteLib/archive/refs/tags/0.1.tar.gz
Author: Xemulated
Author-email: xemulated@tuta.io
License: mit
Keywords: QOL,xemulated,json
Classifier: Development Status :: 4 - Beta
Classifier: Intended Audience :: Developers
Classifier: Topic :: Software Development :: Build Tools
Classifier: License :: OSI Approved :: MIT License
Classifier: Programming Language :: Python :: 3.11
Classifier: Programming Language :: Python :: 3.10
